jcapi/__init__.py
jcapi/account.py
jcapi/binary_sensor.py
jcapi/climate.py
jcapi/const.py
jcapi/cover.py
jcapi/director.py
jcapi/error_handling.py
jcapi/event_controller.py
jcapi/light.py
jcapi/lock.py
jcapi/socketio.py
jcapi/switch.py
jcapi-0.1.5.dist-info/LICENSE
jcapi-0.1.5.dist-info/METADATA
jcapi-0.1.5.dist-info/WHEEL
jcapi-0.1.5.dist-info/top_level.txt
jcapi-0.1.5.dist-info/RECORD
